{"cameraMode":{"drawMode":0,"name":"Shaded","section":"Shading Mode"},"sceneLighting":true,"audioPlay":false,"sceneViewState":{"showFog":true,"showMaterialUpdate":false,"showSkybox":true,"showFlares":true,"showImageEffects":true,"showParticleSystems":true},"in2DMode":false,"pivot":{"x":1.2124096155166627,"y":4.489099979400635,"z":-14.580110549926758},"rotation":{"x":-0.10336209833621979,"y":-0.022791394963860513,"z":0.004980965051800013,"w":-0.9945801496505737},"size":10.565129280090332,"orthographic":false}